redshiftutils/__init__.py
redshiftutils-0.0.2.dist-info/METADATA
redshiftutils-0.0.2.dist-info/WHEEL
redshiftutils-0.0.2.dist-info/top_level.txt
redshiftutils-0.0.2.dist-info/RECORD
